fill_dt_data/__init__.py
fill_dt_data/fill_dt_data.py
fill_dt_data-0.0.7.dist-info/METADATA
fill_dt_data-0.0.7.dist-info/WHEEL
fill_dt_data-0.0.7.dist-info/licenses/LICENSE
fill_dt_data-0.0.7.dist-info/RECORD
