Metadata-Version: 2.1
Name: fill_dt_data
Version: 0.0.7
Summary: A tool to fill column values in Pandas
Project-URL: Homepage, https://github.com/C-Williams/spiced_projects/tree/main/fill_dt_data
Project-URL: Bug Tracker, https://github.com/C-Williams/spiced_projects/issues
Author-email: Chris Williams <20cwilliams09@gmail.com>
License-File: LICENSE
Classifier: License :: OSI Approved :: MIT License
Classifier: Operating System :: OS Independent
Classifier: Programming Language :: Python :: 3
Requires-Python: >=3.8
Requires-Dist: pandas>=1.5.2
